{"cameraMode":{"drawMode":0,"name":"Shaded","section":"Shading Mode"},"sceneLighting":true,"audioPlay":false,"sceneViewState":{"showFog":true,"showMaterialUpdate":false,"showSkybox":false,"showFlares":true,"showImageEffects":true,"showParticleSystems":true,"showVisualEffectGraphs":true,"m_FxEnabled":true},"in2DMode":false,"pivot":{"x":-4.827111721038818,"y":9.311583518981934,"z":-5.346107482910156},"rotation":{"x":-0.30212798714637759,"y":0.6700736880302429,"z":-0.3478373885154724,"w":-0.5820348858833313},"size":17.723026275634767,"orthographic":false}